calcpackage/__init__.py
taruncalc-0.1.0.dist-info/LICENSE.txt
taruncalc-0.1.0.dist-info/METADATA
taruncalc-0.1.0.dist-info/WHEEL
taruncalc-0.1.0.dist-info/top_level.txt
taruncalc-0.1.0.dist-info/RECORD
