Metadata-Version: 2.1
Name: taruncalc
Version: 0.1.0
Summary: It is calculator app
Home-page: UNKNOWN
Author: Tarun
Author-email: gangadhartarun21@gmail.com
License: UNKNOWN
Platform: UNKNOWN
Classifier: Programming Language :: Python :: 3
Classifier: License :: OSI Approved :: MIT License
Classifier: Operating System :: OS Independent
License-File: LICENSE.txt
